
[
  {
    "id": 1,
    "title": "Beachside Cottage",
    "price": "450000",
    "address": "123 Ocean Blvd, Fort Walton Beach, FL",
    "bedrooms": 3,
    "bathrooms": 2,
    "sqft": 1800,
    "imageUrl": "/property-2.jpg",
    "imageHint": "beach cottage"
  },
  {
    "id": 2,
    "title": "Modern Downtown Condo",
    "price": "320000",
    "address": "456 Main St, Fort Walton Beach, FL",
    "bedrooms": 2,
    "bathrooms": 2,
    "sqft": 1200,
    "imageUrl": "/property-3.jpg",
    "imageHint": "modern condo"
  },
  {
    "id": 3,
    "title": "Spacious Family Home",
    "price": "580000",
    "address": "789 Suburbia Ln, Fort Walton Beach, FL",
    "bedrooms": 4,
    "bathrooms": 3,
    "sqft": 2500,
    "imageUrl": "/property-4.jpg",
    "imageHint": "suburban house"
  }
]
